marshmallow/__init__.py
marshmallow/base.py
marshmallow/class_registry.py
marshmallow/compat.py
marshmallow/decorators.py
marshmallow/exceptions.py
marshmallow/fields.py
marshmallow/marshalling.py
marshmallow/orderedset.py
marshmallow/schema.py
marshmallow/utils.py
marshmallow/validate.py
toastedmarshmallow/__init__.py
toastedmarshmallow/compat.py
toastedmarshmallow/jit.py
toastedmarshmallow/utils.py
toastedmarshmallow/__pycache__/__init__.cpython-36.pyc
toastedmarshmallow/__pycache__/compat.cpython-36.pyc
toastedmarshmallow/__pycache__/jit.cpython-36.pyc
toastedmarshmallow/__pycache__/utils.cpython-36.pyc
toastedmarshmallow-0.2.6.dist-info/DESCRIPTION.rst
toastedmarshmallow-0.2.6.dist-info/METADATA
toastedmarshmallow-0.2.6.dist-info/RECORD
toastedmarshmallow-0.2.6.dist-info/WHEEL
toastedmarshmallow-0.2.6.dist-info/metadata.json
toastedmarshmallow-0.2.6.dist-info/top_level.txt
