Metadata-Version: 2.0
Name: toastedmarshmallow
Version: 0.2.6
Summary: A JIT implementation for Marshmallow to speed up dumping and loading objects.
Home-page: https://github.com/lyft/toastedmarshmallow
Author: Roy Williams
Author-email: rwilliams@lyft.com
License: apache2
Keywords: serialization,rest,json,api,marshal,marshalling,deserialization,validation,schema
Platform: UNKNOWN
Classifier: Development Status :: 5 - Production/Stable
Classifier: Intended Audience :: Developers
Classifier: License :: OSI Approved :: Apache Software License
Classifier: Programming Language :: Python :: 2
Classifier: Programming Language :: Python :: 2.7
Classifier: Programming Language :: Python :: 3
Classifier: Programming Language :: Python :: 3.4
Classifier: Programming Language :: Python :: 3.5
Classifier: Programming Language :: Python :: 3.6
Classifier: Programming Language :: Python :: Implementation :: CPython
Classifier: Programming Language :: Python :: Implementation :: PyPy
Requires-Dist: attrs (>=17.1.0)
Provides-Extra: reco
Requires-Dist: python-dateutil; extra == 'reco'
Requires-Dist: simplejson; extra == 'reco'
